galight/__init__.py
galight/data_process.py
galight/fitting_process.py
galight/fitting_specify.py
galight/hsc_utils/__init__.py
galight/hsc_utils/hsc_image.py
galight/hsc_utils/hsc_psf.py
galight/tools/__init__.py
galight/tools/all_tools.py
galight/tools/astro_tools.py
galight/tools/asymmetry_tools.py
galight/tools/cutout_tools.py
galight/tools/measure_tools.py
galight/tools/plot_tools.py
galight-0.2.1.dist-info/AUTHORS.rst
galight-0.2.1.dist-info/LICENSE
galight-0.2.1.dist-info/METADATA
galight-0.2.1.dist-info/WHEEL
galight-0.2.1.dist-info/top_level.txt
galight-0.2.1.dist-info/RECORD
