Metadata-Version: 2.1
Name: galight
Version: 0.2.1
Summary: Galaxy light 2D modeling tool
Home-page: https://github.com/dartoon/galight
Author: Xuheng Ding
Author-email: xuheng.ding@ipmu.jp
License: MIT
Keywords: galight
Platform: UNKNOWN
Classifier: Development Status :: 2 - Pre-Alpha
Classifier: Intended Audience :: Developers
Classifier: License :: OSI Approved :: MIT License
Classifier: Natural Language :: English
Classifier: Programming Language :: Python :: 2
Classifier: Programming Language :: Python :: 2.6
Classifier: Programming Language :: Python :: 2.7
Classifier: Programming Language :: Python :: 3
Classifier: Programming Language :: Python :: 3.3
Classifier: Programming Language :: Python :: Implementation :: PyPy
License-File: LICENSE
License-File: AUTHORS.rst
